rpki_agent/__init__.py
rpki_agent/__meta__.py
rpki_agent/cli.py
rpki_agent-0.1.0a2.dist-info/LICENSE
rpki_agent-0.1.0a2.dist-info/METADATA
rpki_agent-0.1.0a2.dist-info/WHEEL
rpki_agent-0.1.0a2.dist-info/entry_points.txt
rpki_agent-0.1.0a2.dist-info/top_level.txt
rpki_agent-0.1.0a2.dist-info/RECORD
